convergence/__init__.py
convergence/functions.py
convergence/interface.py
convergence/tables.py
convergence-0.6.7.dist-info/COPYING
convergence-0.6.7.dist-info/METADATA
convergence-0.6.7.dist-info/WHEEL
convergence-0.6.7.dist-info/entry_points.txt
convergence-0.6.7.dist-info/top_level.txt
convergence-0.6.7.dist-info/RECORD
