Metadata-Version: 2.1
Name: convergence
Version: 0.6.7
Summary: A Python program to Perform Calculations Associated with a Grid Convergence Study
Author-email: Mathew Topper <damm_horse@yahoo.co.uk>
Project-URL: Homepage, https://github.com/Data-Only-Greater/convergence
Project-URL: Issues, https://github.com/Data-Only-Greater/convergence/issues
Classifier: Development Status :: 4 - Beta
Classifier: Intended Audience :: Science/Research
Classifier: License :: OSI Approved :: GNU General Public License v3 (GPLv3)
Classifier: Natural Language :: English
Classifier: Operating System :: OS Independent
Classifier: Programming Language :: Python :: 3
Classifier: Programming Language :: Python :: 3.9
Classifier: Programming Language :: Python :: 3.10
Classifier: Programming Language :: Python :: 3.11
Classifier: Programming Language :: Python :: 3.12
Classifier: Programming Language :: Python :: 3.13
Classifier: Topic :: Scientific/Engineering
License-File: COPYING
